gds_template_pack/__init__.py
gds_template_pack/templates/gds/accordion/accordion.html
gds_template_pack/templates/gds/accordion/accordion.yaml
gds_template_pack/templates/gds/back-link/back-link.html
gds_template_pack/templates/gds/back-link/back-link.yaml
gds_template_pack/templates/gds/breadcrumbs/breadcrumbs.html
gds_template_pack/templates/gds/breadcrumbs/breadcrumbs.md
gds_template_pack/templates/gds/breadcrumbs/breadcrumbs.yaml
gds_template_pack/templates/gds/button/button--disabled.html
gds_template_pack/templates/gds/button/button--disabled.yaml
gds_template_pack/templates/gds/button/button--secondary.html
gds_template_pack/templates/gds/button/button--secondary.yaml
gds_template_pack/templates/gds/button/button--start.html
gds_template_pack/templates/gds/button/button--start.yaml
gds_template_pack/templates/gds/button/button--stop-double-click.html
gds_template_pack/templates/gds/button/button--stop-double-click.yaml
gds_template_pack/templates/gds/button/button--warning.html
gds_template_pack/templates/gds/button/button--warning.yaml
gds_template_pack/templates/gds/button/button.html
gds_template_pack/templates/gds/button/button.yaml
gds_template_pack/templates/gds/character-count/character-count.html
gds_template_pack/templates/gds/character-count/character-count.yaml
gds_template_pack/templates/gds/checkboxes/checkboxes.html
gds_template_pack/templates/gds/checkboxes/checkboxes.yaml
gds_template_pack/templates/gds/cookie-banner/cookie-banner.html
gds_template_pack/templates/gds/cookie-banner/cookie-banner.yaml
gds_template_pack/templates/gds/date-input/date-input.html
gds_template_pack/templates/gds/date-input/date-input.yaml
gds_template_pack/templates/gds/details/details.html
gds_template_pack/templates/gds/details/details.yaml
gds_template_pack/templates/gds/error-summary/error-summary.html
gds_template_pack/templates/gds/error-summary/error-summary.yaml
gds_template_pack/templates/gds/fieldset/fieldset.html
gds_template_pack-0.1.1.dist-info/WHEEL
gds_template_pack-0.1.1.dist-info/METADATA
gds_template_pack-0.1.1.dist-info/RECORD
